sindripy/__init__.py
sindripy/_compat.py
sindripy/py.typed
sindripy/mothers/__init__.py
sindripy/mothers/object_mother.py
sindripy/mothers/identifiers/__init__.py
sindripy/mothers/identifiers/string_uuid_primitives_mother.py
sindripy/mothers/primitives/__init__.py
sindripy/mothers/primitives/boolean_primitives_mother.py
sindripy/mothers/primitives/float_primitives_mother.py
sindripy/mothers/primitives/integer_primitives_mother.py
sindripy/mothers/primitives/list_primitives_mother.py
sindripy/mothers/primitives/string_primitives_mother.py
sindripy/value_objects/__init__.py
sindripy/value_objects/aggregate.py
sindripy/value_objects/value_object.py
sindripy/value_objects/decorators/__init__.py
sindripy/value_objects/decorators/validation.py
sindripy/value_objects/errors/__init__.py
sindripy/value_objects/errors/incorrect_value_type_error.py
sindripy/value_objects/errors/invalid_id_format_error.py
sindripy/value_objects/errors/required_value_error.py
sindripy/value_objects/errors/sindri_validation_error.py
sindripy/value_objects/identifiers/__init__.py
sindripy/value_objects/identifiers/string_uuid.py
sindripy/value_objects/primitives/__init__.py
sindripy/value_objects/primitives/boolean.py
sindripy/value_objects/primitives/float.py
sindripy/value_objects/primitives/integer.py
sindripy/value_objects/primitives/list.py
sindripy/value_objects/primitives/string.py
sindripy-0.1.6.dist-info/METADATA
sindripy-0.1.6.dist-info/WHEEL
sindripy-0.1.6.dist-info/licenses/LICENSE
sindripy-0.1.6.dist-info/RECORD
