Metadata-Version: 2.4
Name: sindripy
Version: 0.1.6
Summary: Value Object and Object Mother patterns implementation for Python
Project-URL: documentation, https://dimanu-py.github.io/sindri/home/
Project-URL: repository, https://github.com/dimanu-py/sindri/
Author-email: dimanu-py <dimanu.py@gmail.com>
License: MIT License
License-File: LICENSE
Classifier: Framework :: FastAPI
Classifier: Intended Audience :: Developers
Classifier: Operating System :: OS Independent
Classifier: Programming Language :: Python
Classifier: Programming Language :: Python :: 3
Classifier: Programming Language :: Python :: 3.10
Classifier: Programming Language :: Python :: 3.11
Classifier: Programming Language :: Python :: 3.12
Classifier: Programming Language :: Python :: 3.13
Classifier: Topic :: Software Development :: Libraries
Classifier: Topic :: Software Development :: Libraries :: Python Modules
Classifier: Topic :: Software Development :: Testing :: BDD
Classifier: Topic :: Software Development :: Testing :: Unit
Classifier: Typing :: Typed
Requires-Python: <3.14,>=3.10
